beautiful_date/__init__.py
beautiful_date/beautiful_date.py
beautiful_date/beautiful_timedelta.py
beautiful_date/date_range.py
beautiful_date-2.3.0.dist-info/LICENSE
beautiful_date-2.3.0.dist-info/METADATA
beautiful_date-2.3.0.dist-info/WHEEL
beautiful_date-2.3.0.dist-info/top_level.txt
beautiful_date-2.3.0.dist-info/RECORD
