Metadata-Version: 2.1
Name: beautiful-date
Version: 2.3.0
Summary: Simple and beautiful way to create date and datetime objects in Python.
Home-page: https://github.com/kuzmoyev/beautiful-date
Download-URL: https://github.com/kuzmoyev/beautiful-date/archive/1.0.tar.gz
Author: Yevhen Kuzmovych
Author-email: kuzmovych.goog@gmail.com
License: MIT
Keywords: beautiful,date,simple,timedelta,date-range
Classifier: License :: OSI Approved :: MIT License
Classifier: Natural Language :: English
Classifier: Programming Language :: Python
Classifier: Programming Language :: Python :: 3.5
Classifier: Programming Language :: Python :: 3.6
Classifier: Programming Language :: Python :: 3.7
Classifier: Programming Language :: Python :: 3.8
Classifier: Programming Language :: Python :: 3.9
Classifier: Programming Language :: Python :: 3.10
Classifier: Programming Language :: Python :: 3.11
Requires-Python: >=3.5.0
Provides-Extra: dev
Provides-Extra: tests
License-File: LICENSE
